dj_ansible/__init__.py
dj_ansible/admin.py
dj_ansible/apps.py
dj_ansible/const.py
dj_ansible/exceptions.py
dj_ansible/models.py
dj_ansible/tests.py
dj_ansible/views.py
dj_ansible/ansible_kit/__init__.py
dj_ansible/ansible_kit/callback.py
dj_ansible/ansible_kit/executor.py
dj_ansible/ansible_kit/inventory.py
django_ansible-1.0.3.dist-info/LICENSE
django_ansible-1.0.3.dist-info/METADATA
django_ansible-1.0.3.dist-info/WHEEL
django_ansible-1.0.3.dist-info/top_level.txt
django_ansible-1.0.3.dist-info/RECORD
